{
  "$schema": "https://raw.githubusercontent.com/microsoft/vcpkg-tool/main/docs/vcpkg.schema.json",
  "name": "telegram-bot-cpp",
  "version-string": "1.0.0",
  "builtin-baseline": "ee12231b20c95013c6638d845d04c91559a1d1ff",
  "dependencies": [
    {
      "name": "dlfcn-win32",
      "platform": "windows"
    },
    "boost-asio",
    "boost-system",
    "boost-program-options",
    "boost-units",
    "curl",
    "libxml2",
    "libgit2",
    "libpng",
    "libwebp",
    "libjpeg-turbo",
    "opencv4",
    "fmt",
    "sqlite3",
    "nlohmann-json",
    "openssl",
    "zlib",
    "cpp-httplib",
    "fruit",
    "cpptrace",
    "abseil",
    "protobuf",
    "gtest",
    "sol2",
    "libarchive"
  ]
}